{
    "projectInfo": [
        {
            "favourable": "",
            "promotionTags": [],
            "logicLabelInfo": {},
            "siteStatus": 3,
            "isEticket": true,
            "collectNum": 0,
            "recReasonType": 2,
            "tours": "",
            "cityName": "深圳",
            "subTitle": "一个陌生女人的来信",
            "venueId": 270,
            "subHead": "这是一个关于胃和阴道的故事。",
            "id": 148280,
            "isSelectSeat": true,
            "venueCity": "深圳",
            "actores": "",
            "nearestPerformTime": 1532520000000,
            "isNewItem": 0,
            "showTag": "",
            "showTime": "2018.07.25-07.29",
            "logicAddress": "深圳",
            "ipvuv": 549,
            "venueName": "深圳市少年宫剧场",
            "priceStr": "100,180,280,380",
            "isGeneralAgent": true,
            "tourProjects": [],
            "name": "MaiLive 孟京辉戏剧作品《一个陌生女人的来信》深圳站",
            "verticalPic": "https://pimg.dmcdn.cn/perform/project/1482/148280_n.jpg?_t=1523518063361",
            "formattedPriceStr": "100-380"
        },
        {
            "favourable": "",
            "promotionTags": [],
            "logicLabelInfo": {},
            "siteStatus": 3,
            "isEticket": false,
            "collectNum": 0,
            "recReasonType": 2,
            "tours": "",
            "cityName": "深圳",
            "subTitle": "麦克白",
            "venueId": 270,
            "subHead": "莎士比亚四大悲剧中最血腥诡异的作品，写出人性本恶及在心魔诱惑下的挣扎",
            "id": 155033,
            "isSelectSeat": true,
            "venueCity": "深圳",
            "actores": "",
            "nearestPerformTime": 1544355000000,
            "isNewItem": 0,
            "showTag": "",
            "showTime": "2018.12.09 19:30",
            "logicAddress": "深圳",
            "ipvuv": 178,
            "venueName": "深圳市少年宫剧场",
            "priceStr": "80,160,240,360",
            "isGeneralAgent": true,
            "tourProjects": [],
            "name": "英国TNT剧院原版莎翁经典话剧《麦克白》",
            "verticalPic": "https://pimg.dmcdn.cn/perform/project/1550/155033_n.jpg?_t=1529063328226",
            "formattedPriceStr": "80-360"
        },
        {
            "favourable": "",
            "promotionTags": [],
            "logicLabelInfo": {},
            "siteStatus": 3,
            "isEticket": true,
            "collectNum": 0,
            "recReasonType": 2,
            "tours": "",
            "cityName": "深圳",
            "subTitle": "早安，南美",
            "venueId": 270,
            "subHead": "在智利、巴西、墨西哥、加拿大、西班牙和瑞士进行了巡演，如今已经成为全世界各大艺术节的邀请剧目。",
            "id": 153714,
            "isSelectSeat": true,
            "venueCity": "深圳",
            "actores": "",
            "nearestPerformTime": 1537756200000,
            "isNewItem": 0,
            "showTag": "",
            "showTime": "2018.09.24",
            "logicAddress": "深圳",
            "ipvuv": 25,
            "venueName": "深圳市少年宫剧场",
            "priceStr": "80,120,160,200",
            "isGeneralAgent": true,
            "tourProjects": [],
            "name": "智利亲子音乐旅行剧《早安，南美》",
            "verticalPic": "https://pimg.dmcdn.cn/perform/project/1537/153714_n.jpg?_t=1528357057153",
            "formattedPriceStr": "80-200"
        },
        {
            "favourable": "",
            "promotionTags": [],
            "logicLabelInfo": {},
            "siteStatus": 2,
            "isEticket": false,
            "collectNum": 0,
            "recReasonType": 2,
            "tours": "",
            "cityName": "深圳",
            "subTitle": "阿拉丁神灯",
            "venueId": 270,
            "subHead": "与阿拉丁相约，开启神奇的魔法冒险之旅！",
            "id": 142763,
            "isSelectSeat": false,
            "venueCity": "深圳",
            "actores": "",
            "nearestPerformTime": 1538879400000,
            "isNewItem": 0,
            "showTag": "",
            "showTime": "2018.10.07",
            "logicAddress": "深圳",
            "ipvuv": 2,
            "venueName": "深圳市少年宫剧场",
            "priceStr": "价格待定",
            "isGeneralAgent": false,
            "tourProjects": [],
            "name": "【小橙堡】魔幻亲子儿童剧《阿拉丁神灯》",
            "verticalPic": "https://pimg.dmcdn.cn/perform/project/1427/142763_n.jpg?_t=1517566349539",
            "formattedPriceStr": "价格待定"
        },
        {
            "favourable": "",
            "promotionTags": [],
            "logicLabelInfo": {},
            "siteStatus": 3,
            "isEticket": true,
            "collectNum": 0,
            "recReasonType": 2,
            "tours": "",
            "cityName": "深圳",
            "subTitle": "尼尔斯骑鹅历险记",
            "venueId": 270,
            "subHead": "史上，唯一一部荣获诺贝尔文学奖的童话作品。<br />",
            "id": 157461,
            "isSelectSeat": true,
            "venueCity": "深圳",
            "actores": "",
            "nearestPerformTime": 1539484200000,
            "isNewItem": 0,
            "showTag": "",
            "showTime": "2018.10.14",
            "logicAddress": "深圳",
            "ipvuv": 22,
            "venueName": "深圳市少年宫剧场",
            "priceStr": "80,180,280",
            "isGeneralAgent": true,
            "tourProjects": [],
            "name": "大型原创童话音乐剧《尼尔斯骑鹅历险记》",
            "verticalPic": "https://pimg.dmcdn.cn/perform/project/1574/157461_n.jpg?_t=1531126181820",
            "formattedPriceStr": "80-280"
        },
        {
            "favourable": "",
            "promotionTags": [],
            "logicLabelInfo": {},
            "siteStatus": 3,
            "isEticket": true,
            "collectNum": 0,
            "recReasonType": 2,
            "tours": "",
            "cityName": "深圳",
            "subTitle": "环游世界",
            "venueId": 270,
            "subHead": "给孩子一把钥匙，开启孩子音乐梦想！",
            "id": 157463,
            "isSelectSeat": true,
            "venueCity": "深圳",
            "actores": "",
            "nearestPerformTime": 1543113000000,
            "isNewItem": 0,
            "showTag": "",
            "showTime": "2018.11.25",
            "logicAddress": "深圳",
            "ipvuv": 9,
            "venueName": "深圳市少年宫剧场",
            "priceStr": "80,180,280,380",
            "isGeneralAgent": true,
            "tourProjects": [],
            "name": "音乐的奥妙《环游世界》亲子互动音乐会",
            "verticalPic": "https://pimg.dmcdn.cn/perform/project/1574/157463_n.jpg?_t=1531120752690",
            "formattedPriceStr": "80-380"
        },
        {
            "favourable": "",
            "promotionTags": [],
            "logicLabelInfo": {},
            "siteStatus": 3,
            "isEticket": true,
            "collectNum": 0,
            "recReasonType": 2,
            "tours": "",
            "cityName": "深圳",
            "subTitle": "白雪公主和七个小矮人",
            "venueId": 270,
            "subHead": "故事主要讲述白雪公主因为美丽漂亮而被其后母妒忌，发誓要把她置于死地",
            "id": 151035,
            "isSelectSeat": true,
            "venueCity": "深圳",
            "actores": "",
            "nearestPerformTime": 1540089000000,
            "isNewItem": 0,
            "showTag": "",
            "showTime": "2018.10.21",
            "logicAddress": "深圳",
            "ipvuv": 70,
            "venueName": "深圳市少年宫剧场",
            "priceStr": "100,160,200",
            "isGeneralAgent": true,
            "tourProjects": [],
            "name": "大型人偶音乐童话剧《白雪公主和七个小矮人》 Snow White and the Seven Dwarfs",
            "verticalPic": "https://pimg.dmcdn.cn/perform/project/1510/151035_n.jpg?_t=1526035393956",
            "formattedPriceStr": "100-200"
        },
        {
            "favourable": "",
            "promotionTags": [],
            "logicLabelInfo": {},
            "siteStatus": 3,
            "isEticket": false,
            "collectNum": 0,
            "recReasonType": 2,
            "tours": "",
            "cityName": "深圳",
            "subTitle": "理智与情感",
            "venueId": 270,
            "subHead": "《理智与情感》讲述了一对姐妹曲折的择偶故事。",
            "id": 155035,
            "isSelectSeat": true,
            "venueCity": "深圳",
            "actores": "",
            "nearestPerformTime": 1541935800000,
            "isNewItem": 0,
            "showTag": "",
            "showTime": "2018.11.11 19:00",
            "logicAddress": "深圳",
            "ipvuv": 60,
            "venueName": "深圳市少年宫剧场",
            "priceStr": "80,160,240,360",
            "isGeneralAgent": true,
            "tourProjects": [],
            "name": "英国书屋剧院英伦经典系列《理智与情感》",
            "verticalPic": "https://pimg.dmcdn.cn/perform/project/1550/155035_n.jpg?_t=1529062514732",
            "formattedPriceStr": "80-360"
        },
        {
            "favourable": "",
            "promotionTags": [],
            "logicLabelInfo": {},
            "siteStatus": 3,
            "isEticket": true,
            "collectNum": 0,
            "recReasonType": 2,
            "tours": "",
            "cityName": "深圳",
            "subTitle": "三只小猪",
            "venueId": 827014,
            "subHead": "集趣味性、艺术性、哲理性融为一体",
            "id": 156939,
            "isSelectSeat": true,
            "venueCity": "深圳",
            "actores": "",
            "nearestPerformTime": 1532743200000,
            "isNewItem": 0,
            "showTag": "",
            "showTime": "2018.7.28 10:00",
            "logicAddress": "深圳",
            "ipvuv": 62,
            "venueName": "刘老根拿来一壶嗨晚宴剧院",
            "priceStr": "108,148",
            "isGeneralAgent": true,
            "tourProjects": [],
            "name": "《三只小猪》",
            "verticalPic": "https://pimg.dmcdn.cn/perform/project/1569/156939_n.jpg?_t=1530694868094",
            "formattedPriceStr": "108-148"
        },
        {
            "favourable": "",
            "promotionTags": [],
            "logicLabelInfo": {},
            "siteStatus": 3,
            "isEticket": true,
            "collectNum": 0,
            "recReasonType": 2,
            "tours": "",
            "cityName": "深圳",
            "subTitle": "白雪公主和七个小矮人",
            "venueId": 827014,
            "subHead": "带你走进白雪公主与王子的奇幻世界",
            "id": 156985,
            "isSelectSeat": true,
            "venueCity": "深圳",
            "actores": "",
            "nearestPerformTime": 1532764800000,
            "isNewItem": 0,
            "showTag": "",
            "showTime": "2018.07.28  16:00",
            "logicAddress": "深圳",
            "ipvuv": 116,
            "venueName": "刘老根拿来一壶嗨晚宴剧院",
            "priceStr": "108,148",
            "isGeneralAgent": true,
            "tourProjects": [],
            "name": "《白雪公主和七个小矮人》",
            "verticalPic": "https://pimg.dmcdn.cn/perform/project/1569/156985_n.jpg?_t=1530699629694",
            "formattedPriceStr": "108-148"
        }
    ],
    "loadmore": [
        {
            "favourable": "",
            "promotionTags": [],
            "logicLabelInfo": {
                "staticLabelInfo": {
                    "BRAND_CLASS": ["爱乐汇"]
                }
            },
            "siteStatus": 3,
            "isEticket": false,
            "collectNum": 0,
            "recReasonType": 2,
            "tours": "",
            "cityName": "深圳",
            "subTitle": "美国全美男童合唱团深圳音乐会",
            "venueId": 270,
            "subHead": "全美男童合唱团是世界上不同凡响的童声合唱团，他们的艺术特色独具一格",
            "id": 150770,
            "isSelectSeat": true,
            "venueCity": "深圳",
            "actores": "",
            "nearestPerformTime": 1532174400000,
            "isNewItem": 0,
            "showTag": "",
            "showTime": "2018.07.21  20:00",
            "logicAddress": "深圳",
            "ipvuv": 75,
            "venueName": "深圳市少年宫剧场",
            "priceStr": "180,280,380,480,580",
            "isGeneralAgent": true,
            "tourProjects": [],
            "name": "爱乐汇·聆听\"天籁之音\" 美国全美男童合唱团深圳音乐会",
            "verticalPic": "https://pimg.dmcdn.cn/perform/project/1507/150770_n.jpg?_t=1525934129325",
            "formattedPriceStr": "180-580"
        },
        {
            "favourable": "",
            "promotionTags": [],
            "logicLabelInfo": {},
            "siteStatus": 3,
            "isEticket": true,
            "collectNum": 0,
            "recReasonType": 2,
            "tours": "",
            "cityName": "深圳",
            "subTitle": "白雪公主和七个小矮人",
            "venueId": 270,
            "subHead": "故事主要讲述白雪公主因为美丽漂亮而被其后母妒忌，发誓要把她置于死地",
            "id": 151035,
            "isSelectSeat": true,
            "venueCity": "深圳",
            "actores": "",
            "nearestPerformTime": 1540089000000,
            "isNewItem": 0,
            "showTag": "",
            "showTime": "2018.10.21",
            "logicAddress": "深圳",
            "ipvuv": 70,
            "venueName": "深圳市少年宫剧场",
            "priceStr": "100,160,200",
            "isGeneralAgent": true,
            "tourProjects": [],
            "name": "大型人偶音乐童话剧《白雪公主和七个小矮人》 Snow White and the Seven Dwarfs",
            "verticalPic": "https://pimg.dmcdn.cn/perform/project/1510/151035_n.jpg?_t=1526035393956",
            "formattedPriceStr": "100-200"
        },
        {
            "favourable": "",
            "promotionTags": [],
            "logicLabelInfo": {},
            "siteStatus": 3,
            "isEticket": true,
            "collectNum": 0,
            "recReasonType": 2,
            "tours": "",
            "cityName": "深圳",
            "subTitle": "早安，南美",
            "venueId": 270,
            "subHead": "在智利、巴西、墨西哥、加拿大、西班牙和瑞士进行了巡演，如今已经成为全世界各大艺术节的邀请剧目。",
            "id": 153714,
            "isSelectSeat": true,
            "venueCity": "深圳",
            "actores": "",
            "nearestPerformTime": 1537756200000,
            "isNewItem": 0,
            "showTag": "",
            "showTime": "2018.09.24",
            "logicAddress": "深圳",
            "ipvuv": 25,
            "venueName": "深圳市少年宫剧场",
            "priceStr": "80,120,160,200",
            "isGeneralAgent": true,
            "tourProjects": [],
            "name": "智利亲子音乐旅行剧《早安，南美》",
            "verticalPic": "https://pimg.dmcdn.cn/perform/project/1537/153714_n.jpg?_t=1528357057153",
            "formattedPriceStr": "80-200"
        },
        {
            "favourable": "",
            "promotionTags": [],
            "logicLabelInfo": {},
            "siteStatus": 2,
            "isEticket": false,
            "collectNum": 0,
            "recReasonType": 2,
            "tours": "",
            "cityName": "深圳",
            "subTitle": "阿拉丁神灯",
            "venueId": 270,
            "subHead": "与阿拉丁相约，开启神奇的魔法冒险之旅！",
            "id": 142763,
            "isSelectSeat": false,
            "venueCity": "深圳",
            "actores": "",
            "nearestPerformTime": 1538879400000,
            "isNewItem": 0,
            "showTag": "",
            "showTime": "2018.10.07",
            "logicAddress": "深圳",
            "ipvuv": 2,
            "venueName": "深圳市少年宫剧场",
            "priceStr": "价格待定",
            "isGeneralAgent": false,
            "tourProjects": [],
            "name": "【小橙堡】魔幻亲子儿童剧《阿拉丁神灯》",
            "verticalPic": "https://pimg.dmcdn.cn/perform/project/1427/142763_n.jpg?_t=1517566349539",
            "formattedPriceStr": "价格待定"
        },
        {
            "favourable": "",
            "promotionTags": [],
            "logicLabelInfo": {},
            "siteStatus": 3,
            "isEticket": true,
            "collectNum": 0,
            "recReasonType": 2,
            "tours": "",
            "cityName": "深圳",
            "subTitle": "尼尔斯骑鹅历险记",
            "venueId": 270,
            "subHead": "史上，唯一一部荣获诺贝尔文学奖的童话作品。<br />",
            "id": 157461,
            "isSelectSeat": true,
            "venueCity": "深圳",
            "actores": "",
            "nearestPerformTime": 1539484200000,
            "isNewItem": 0,
            "showTag": "",
            "showTime": "2018.10.14",
            "logicAddress": "深圳",
            "ipvuv": 22,
            "venueName": "深圳市少年宫剧场",
            "priceStr": "80,180,280",
            "isGeneralAgent": true,
            "tourProjects": [],
            "name": "大型原创童话音乐剧《尼尔斯骑鹅历险记》",
            "verticalPic": "https://pimg.dmcdn.cn/perform/project/1574/157461_n.jpg?_t=1531126181820",
            "formattedPriceStr": "80-280"
        },
        {
            "favourable": "",
            "promotionTags": [],
            "logicLabelInfo": {},
            "siteStatus": 3,
            "isEticket": false,
            "collectNum": 0,
            "recReasonType": 2,
            "tours": "",
            "cityName": "深圳",
            "subTitle": "海底两万里",
            "venueId": 270,
            "subHead": "迪士尼歌舞编排 韵味无穷",
            "id": 158320,
            "isSelectSeat": false,
            "venueCity": "深圳",
            "actores": "",
            "nearestPerformTime": 1542508200000,
            "isNewItem": 0,
            "showTag": "",
            "showTime": "2018.11.18",
            "logicAddress": "深圳",
            "ipvuv": 0,
            "venueName": "深圳市少年宫剧场",
            "priceStr": "100,180,280,380,460,740,999",
            "isGeneralAgent": false,
            "tourProjects": [],
            "name": "【小橙堡】3D多媒体海洋历险科幻剧《海底两万里》-深圳站",
            "verticalPic": "https://pimg.dmcdn.cn/perform/project/1583/158320_n.jpg?_t=1531811139647",
            "formattedPriceStr": "100-999"
        },
        {
            "favourable": "",
            "promotionTags": [],
            "logicLabelInfo": {},
            "siteStatus": 3,
            "isEticket": true,
            "collectNum": 0,
            "recReasonType": 2,
            "tours": "",
            "cityName": "深圳",
            "subTitle": "三只小猪",
            "venueId": 827014,
            "subHead": "集趣味性、艺术性、哲理性融为一体",
            "id": 156939,
            "isSelectSeat": true,
            "venueCity": "深圳",
            "actores": "",
            "nearestPerformTime": 1532743200000,
            "isNewItem": 0,
            "showTag": "",
            "showTime": "2018.7.28 10:00",
            "logicAddress": "深圳",
            "ipvuv": 62,
            "venueName": "刘老根拿来一壶嗨晚宴剧院",
            "priceStr": "108,148",
            "isGeneralAgent": true,
            "tourProjects": [],
            "name": "《三只小猪》",
            "verticalPic": "https://pimg.dmcdn.cn/perform/project/1569/156939_n.jpg?_t=1530694868094",
            "formattedPriceStr": "108-148"
        },
        {
            "favourable": "",
            "promotionTags": [],
            "logicLabelInfo": {},
            "siteStatus": 3,
            "isEticket": true,
            "collectNum": 0,
            "recReasonType": 2,
            "tours": "",
            "cityName": "深圳",
            "subTitle": "刘老根拿来一壶嗨晚宴剧院",
            "venueId": 827014,
            "subHead": "集大型演艺、美食、娱乐三位于一体的娱乐剧院",
            "id": 158036,
            "isSelectSeat": true,
            "venueCity": "深圳",
            "actores": "",
            "nearestPerformTime": 1532257200000,
            "isNewItem": 0,
            "showTag": "",
            "showTime": "2018.07.22-08.11",
            "logicAddress": "深圳",
            "ipvuv": 193,
            "venueName": "刘老根拿来一壶嗨晚宴剧院",
            "priceStr": "39,95,138,300,368,552,600,1000,1580,1880,1980,2380",
            "isGeneralAgent": false,
            "tourProjects": [],
            "name": "深圳.刘老根拿来一壶嗨晚宴剧院",
            "verticalPic": "https://pimg.dmcdn.cn/perform/project/1580/158036_n.jpg?_t=1531469652607",
            "formattedPriceStr": "39-2380"
        },
        {
            "favourable": "",
            "promotionTags": [],
            "logicLabelInfo": {},
            "siteStatus": 3,
            "isEticket": true,
            "collectNum": 0,
            "recReasonType": 2,
            "tours": "",
            "cityName": "深圳",
            "subTitle": "白雪公主和七个小矮人",
            "venueId": 827014,
            "subHead": "带你走进白雪公主与王子的奇幻世界",
            "id": 156985,
            "isSelectSeat": true,
            "venueCity": "深圳",
            "actores": "",
            "nearestPerformTime": 1532764800000,
            "isNewItem": 0,
            "showTag": "",
            "showTime": "2018.07.28  16:00",
            "logicAddress": "深圳",
            "ipvuv": 116,
            "venueName": "刘老根拿来一壶嗨晚宴剧院",
            "priceStr": "108,148",
            "isGeneralAgent": true,
            "tourProjects": [],
            "name": "《白雪公主和七个小矮人》",
            "verticalPic": "https://pimg.dmcdn.cn/perform/project/1569/156985_n.jpg?_t=1530699629694",
            "formattedPriceStr": "108-148"
        },
        {
            "favourable": "",
            "promotionTags": [],
            "logicLabelInfo": {},
            "siteStatus": 3,
            "isEticket": false,
            "collectNum": 0,
            "recReasonType": 2,
            "tours": "",
            "cityName": "深圳",
            "subTitle": "白雪公主",
            "venueId": 91731,
            "subHead": "怎样才能拥有幸福？不仅需要善良，更需要智慧、勇气和强健的体魄",
            "id": 139315,
            "isSelectSeat": false,
            "venueCity": "深圳",
            "actores": "",
            "nearestPerformTime": 1544236200000,
            "isNewItem": 0,
            "showTag": "",
            "showTime": "2018.12.08-12.15",
            "logicAddress": "深圳",
            "ipvuv": 15,
            "venueName": "深圳妇儿大厦儿童剧场",
            "priceStr": "50,60,100",
            "isGeneralAgent": false,
            "tourProjects": [],
            "name": "【小橙堡】奇思妙想童话剧《白雪公主》",
            "verticalPic": "https://pimg.dmcdn.cn/perform/project/1393/139315_n.jpg",
            "formattedPriceStr": "50-100"
        }
    ],
    "hotSearch": {
        "api": "mtop.damai.wireless.search.discovery.bycity.get",
        "data": {
            "result": {
                "data": [
                    {
                        "action": 1,
                        "alg": "099e1080-4f57-41d2-9dcb-749a50e34086_16823",
                        "url": "",
                        "word": "九周年庆典",
                        "wordType": 5
                    },
                    {
                        "action": 1,
                        "alg": "099e1080-4f57-41d2-9dcb-749a50e34086_16823",
                        "url": "",
                        "word": "外场嘉年华",
                        "wordType": 5
                    },
                    {
                        "action": 1,
                        "alg": "099e1080-4f57-41d2-9dcb-749a50e34086_16823",
                        "url": "",
                        "word": "薛之谦",
                        "wordType": 5
                    },
                    {
                        "action": 1,
                        "alg": "099e1080-4f57-41d2-9dcb-749a50e34086_16823",
                        "url": "",
                        "word": "张学友",
                        "wordType": 5
                    },
                    {
                        "action": 1,
                        "alg": "099e1080-4f57-41d2-9dcb-749a50e34086_16823",
                        "url": "",
                        "word": "五月天",
                        "wordType": 5
                    },
                    {
                        "action": 1,
                        "alg": "099e1080-4f57-41d2-9dcb-749a50e34086_16823",
                        "url": "",
                        "word": "岳云鹏",
                        "wordType": 5
                    },
                    {
                        "action": 1,
                        "alg": "099e1080-4f57-41d2-9dcb-749a50e34086_16823",
                        "url": "",
                        "word": "寻梦海底两万里-深海之光展",
                        "wordType": 5
                    },
                    {
                        "action": 1,
                        "alg": "099e1080-4f57-41d2-9dcb-749a50e34086_16823",
                        "url": "",
                        "word": "国际潮流玩具展",
                        "wordType": 5
                    }
                ]
            }
        },
        "ret": ["SUCCESS::调用成功"],
        "v": "1.0"
    }
}
